rv/__init__.py
rv/api.py
rv/cmidmap.py
rv/container.py
rv/controller.py
rv/errors.py
rv/note.py
rv/option.py
rv/pattern.py
rv/project.py
rv/synth.py
rv/_vendor/__init__.py
rv/_vendor/chunk.py
rv/chunks/__init__.py
rv/chunks/array.py
rv/chunks/chunk.py
rv/chunks/drawnwaveform.py
rv/chunks/waveform.py
rv/lib/__init__.py
rv/lib/conversions.py
rv/lib/iff.py
rv/lib/validators.py
rv/modules/__init__.py
rv/modules/adsr.py
rv/modules/amplifier.py
rv/modules/analoggenerator.py
rv/modules/compressor.py
rv/modules/ctl2note.py
rv/modules/dcblocker.py
rv/modules/delay.py
rv/modules/distortion.py
rv/modules/drumsynth.py
rv/modules/echo.py
rv/modules/eq.py
rv/modules/feedback.py
rv/modules/fft.py
rv/modules/filter.py
rv/modules/filterpro.py
rv/modules/flanger.py
rv/modules/fm.py
rv/modules/fmx.py
rv/modules/generator.py
rv/modules/glide.py
rv/modules/gpio.py
rv/modules/input.py
rv/modules/kicker.py
rv/modules/lfo.py
rv/modules/loop.py
rv/modules/meta.py
rv/modules/metamodule.py
rv/modules/modulator.py
rv/modules/module.py
rv/modules/multictl.py
rv/modules/multisynth.py
rv/modules/output.py
rv/modules/pitch2ctl.py
rv/modules/pitchdetector.py
rv/modules/pitchshifter.py
rv/modules/reverb.py
rv/modules/sampler.py
rv/modules/smooth.py
rv/modules/sound2ctl.py
rv/modules/spectravoice.py
rv/modules/velocity2ctl.py
rv/modules/vibrato.py
rv/modules/vocalfilter.py
rv/modules/vorbisplayer.py
rv/modules/waveshaper.py
rv/modules/base/__init__.py
rv/modules/base/adsr.py
rv/modules/base/amplifier.py
rv/modules/base/analoggenerator.py
rv/modules/base/compressor.py
rv/modules/base/ctl2note.py
rv/modules/base/dcblocker.py
rv/modules/base/delay.py
rv/modules/base/distortion.py
rv/modules/base/drumsynth.py
rv/modules/base/echo.py
rv/modules/base/eq.py
rv/modules/base/feedback.py
rv/modules/base/fft.py
rv/modules/base/filter.py
rv/modules/base/filterpro.py
rv/modules/base/flanger.py
rv/modules/base/fm.py
rv/modules/base/fmx.py
rv/modules/base/generator.py
rv/modules/base/glide.py
radiant_voices-2.0.0.2.1.2.1.dist-info/METADATA
radiant_voices-2.0.0.2.1.2.1.dist-info/WHEEL
radiant_voices-2.0.0.2.1.2.1.dist-info/licenses/AUTHORS.rst
radiant_voices-2.0.0.2.1.2.1.dist-info/licenses/LICENSE
radiant_voices-2.0.0.2.1.2.1.dist-info/RECORD
