Metadata-Version: 2.4
Name: radiant-voices
Version: 2.0.0.2.1.2.1
Summary: Create, read, modify, and write SunVox files.
Author-email: Matthew Scott <matt@11craft.com>
License-File: AUTHORS.rst
License-File: LICENSE
Requires-Python: >=3.11
Requires-Dist: attrs>=25.1.0
Requires-Dist: logutils>=0.3.5
Requires-Dist: networkx>=3.4.2
Requires-Dist: python-slugify>=8.0.4
Provides-Extra: tools
Requires-Dist: numpy>=2.2.3; extra == 'tools'
Requires-Dist: rich>=13.9.4; extra == 'tools'
Requires-Dist: scipy>=1.15.2; extra == 'tools'
Requires-Dist: sunvox-dll-python>=0.3.6.2.1.2.1; extra == 'tools'
Requires-Dist: tqdm>=4.67.1; extra == 'tools'
